Python_Machine/Cell.py
Python_Machine/CellMachine.py
Python_Machine/Enums.py
Python_Machine/Grid.py
Python_Machine/Utils.py
Python_Machine/__init__.py
Python_Machine/base74.py
Python_Machine/py.typed
Python_Machine/textures/CC_spinner.png
Python_Machine/textures/C_spinner.png
Python_Machine/textures/background.png
Python_Machine/textures/enemy.png
Python_Machine/textures/generator.png
Python_Machine/textures/immobile.png
Python_Machine/textures/mover.png
Python_Machine/textures/placeable.png
Python_Machine/textures/push.png
Python_Machine/textures/slide.png
Python_Machine/textures/trash.png
Python_Machine-1.0.4.dist-info/LICENSE
Python_Machine-1.0.4.dist-info/METADATA
Python_Machine-1.0.4.dist-info/WHEEL
Python_Machine-1.0.4.dist-info/top_level.txt
Python_Machine-1.0.4.dist-info/RECORD
