Metadata-Version: 2.1
Name: Python-Machine
Version: 1.0.4
Summary: a Package that allows you to simulate cell machine in python
Author: youtissoum
License: Apache
Platform: unix
Platform: linux
Platform: osx
Platform: win32
Classifier: Programming Language :: Python :: 3
Classifier: Programming Language :: Python :: 3 :: Only
Classifier: Programming Language :: Python :: 3.9
Classifier: Programming Language :: Python :: 3.10
Requires-Python: >=3.8
License-File: LICENSE
Requires-Dist: Pillow (==9.2.0)
Provides-Extra: testing
Requires-Dist: pytest (>=7.0) ; extra == 'testing'
Requires-Dist: pytest-cov (>=3.0) ; extra == 'testing'
Requires-Dist: mypy (>=0.971) ; extra == 'testing'
Requires-Dist: flake8 (>=5.0) ; extra == 'testing'
Requires-Dist: tox (>=3.26) ; extra == 'testing'
